transform_airflow
